wddasylumclaims/FeatherConvert.py
wddasylumclaims/Keywords.py
wddasylumclaims/WebScrape.py
wddasylumclaims/__init__.py
wddasylumclaims/__main__.py
wddasylumclaims/DbAsylumClaims/Admin.py
wddasylumclaims/DbAsylumClaims/Db.py
wddasylumclaims/DbAsylumClaims/User.py
wddasylumclaims/DbAsylumClaims/__init__.py
wddasylumclaims/DbAsylumClaims/__main__.py
wddasylumclaims-0.0.31.data/data/Lib/site-packages/wddasylumclaims/data/keywords.csv
wddasylumclaims-0.0.31.dist-info/LICENSE
wddasylumclaims-0.0.31.dist-info/METADATA
wddasylumclaims-0.0.31.dist-info/WHEEL
wddasylumclaims-0.0.31.dist-info/entry_points.txt
wddasylumclaims-0.0.31.dist-info/top_level.txt
wddasylumclaims-0.0.31.dist-info/RECORD
