Metadata-Version: 2.1
Name: wddasylumclaims
Version: 0.0.31
Summary: ('Asylum Seekers Claims scrapping of data', 'from web and analysis of outcomes')
Home-page: https://github.com/benknight135/wdd-asylum-claims
Author: Ben Knight
Author-email: benknight135@gmail.com
License: License :: OSI Approved :: GPL3
Keywords: wdd asylum seekers claims webscrape wddasylumclaims
Platform: UNKNOWN
Classifier: Development Status :: 3 - Alpha
Classifier: Topic :: Utilities
Classifier: License :: OSI Approved :: MIT License
Requires-Dist: requests
Requires-Dist: bs4
Requires-Dist: pandas
Requires-Dist: feather-format
Requires-Dist: numpy
Requires-Dist: argparse
Requires-Dist: pypiwin32
Requires-Dist: regex
Requires-Dist: pyodbc
